nicopy/__init__.py
nicopy/exception.py
nicopy/nicopy.py
nicopy-1.2.1.dist-info/DESCRIPTION.rst
nicopy-1.2.1.dist-info/METADATA
nicopy-1.2.1.dist-info/RECORD
nicopy-1.2.1.dist-info/WHEEL
nicopy-1.2.1.dist-info/metadata.json
nicopy-1.2.1.dist-info/top_level.txt
