Metadata-Version: 2.0
Name: nicopy
Version: 1.2.1
Summary: niconico api for python
Home-page: http://github.com/roronya/nicopy
Author: roronya
Author-email: roronya628@gmail.com
License: MIT
Keywords: niconico api
Platform: UNKNOWN
Classifier: Development Status :: 5 - Production/Stable
Classifier: Intended Audience :: Developers
Classifier: Topic :: Software Development :: Libraries
Classifier: License :: OSI Approved :: MIT License
Classifier: Programming Language :: Python :: 3
Requires-Dist: beautifulsoup4
Requires-Dist: lxml
Requires-Dist: requests
